devon/__init__.py
devon/devon.py
devon-0.1.1.dist-info/DESCRIPTION.rst
devon-0.1.1.dist-info/METADATA
devon-0.1.1.dist-info/metadata.json
devon-0.1.1.dist-info/RECORD
devon-0.1.1.dist-info/top_level.txt
devon-0.1.1.dist-info/WHEEL
