Metadata-Version: 2.0
Name: devon
Version: 0.1.1
Summary: Uzbek NLP library
Home-page: https://github.com/muminoff/devon
Author: Sardor Muminov
Author-email: smuminov@gmail.com
License: MIT
